test.py
proxysocksgen-1.0.0.dist-info/METADATA
proxysocksgen-1.0.0.dist-info/WHEEL
proxysocksgen-1.0.0.dist-info/top_level.txt
proxysocksgen-1.0.0.dist-info/RECORD
